{
    "poniedzialek": [
        null,
        null,
        null,
        null,
        [
            [
                "1A"
            ],
            "Bezpieczeństwoihigienapracy",
            "B102"
        ],
        [
            [
                "1B"
            ],
            "Edukacjadlabezpieczeństwa",
            "B102"
        ],
        [
            [
                "3A"
            ],
            "Podstawyprzedsiębiorczości",
            "B102"
        ],
        [
            [
                "3F"
            ],
            "Podstawyprzedsiębiorczości",
            "B102"
        ],
        null,
        null,
        null
    ],
    "wtorek": [
        null,
        null,
        null,
        null,
        null,
        null,
        null,
        [
            [
                "3D"
            ],
            "Podstawyprzedsiębiorczości",
            "33"
        ],
        [
            [
                "1B"
            ],
            "Bezpieczeństwoihigienapracy",
            "33"
        ],
        [
            [
                "1A"
            ],
            "Edukacjadlabezpieczeństwa",
            "33"
        ],
        null
    ],
    "środa": [
        [
            [
                "3B"
            ],
            "Podstawyprzedsiębiorczości",
            "33"
        ],
        null,
        null,
        [
            [
                "1D"
            ],
            "Edukacjadlabezpieczeństwa",
            "33"
        ],
        [
            [
                "1C"
            ],
            "Bezpieczeństwoihigienapracy",
            "33"
        ],
        null,
        null,
        null,
        null,
        null,
        null
    ],
    "czwartek": [
        null,
        null,
        null,
        null,
        null,
        null,
        null,
        [
            [
                "3C"
            ],
            "Podstawyprzedsiębiorczości",
            "B102"
        ],
        null,
        null,
        null
    ],
    "piątek": [
        null,
        null,
        null,
        [
            [
                "1C"
            ],
            "Edukacjadlabezpieczeństwa",
            "33"
        ],
        [
            [
                "1D"
            ],
            "Bezpieczeństwoihigienapracy",
            "33"
        ],
        null,
        [
            [
                "3E"
            ],
            "Podstawyprzedsiębiorczości",
            "33"
        ],
        null,
        null,
        null,
        null
    ]
}