{
    "0": [
        null,
        null,
        [
            "MŁ",
            [
                "2F"
            ],
            "Biznes i zarządzanie"
        ],
        [
            "MŁ",
            [
                "2G"
            ],
            "Biznes i zarządzanie"
        ],
        [
            "MŁ",
            [
                "2F"
            ],
            "Biznes i zarządzanie"
        ],
        [
            "MŁ",
            [
                "4E"
            ],
            "Działalność gospodarcza"
        ],
        null,
        [
            "MŁ",
            [
                "2G"
            ],
            "Biznes i zarządzanie"
        ],
        [
            "MŁ",
            [
                "2C"
            ],
            "Biznes i zarządzanie"
        ],
        null,
        null
    ],
    "1": [
        null,
        [
            "MW",
            [
                "2A"
            ],
            "Matematyka"
        ],
        [
            "MW",
            [
                "2A"
            ],
            "Matematyka"
        ],
        [
            "MW",
            [
                "5G"
            ],
            "Matematyka"
        ],
        [
            "MW",
            [
                "5G"
            ],
            "Matematyka"
        ],
        [
            "MW",
            [
                "3A"
            ],
            "Matematyka"
        ],
        [
            "MW",
            [
                "4B"
            ],
            "Chemia"
        ],
        [
            "MW",
            [
                "5C"
            ],
            "Matematyka"
        ],
        [
            "MW",
            [
                "5C"
            ],
            "Matematyka"
        ],
        [
            "MW",
            [
                "5C"
            ],
            "Matematyka Dodatkowa"
        ],
        null
    ],
    "2": [
        null,
        null,
        null,
        [
            "AJ",
            [
                "1A"
            ],
            "Chemia"
        ],
        [
            "OM",
            [
                "1B-1/2"
            ],
            "Język hiszpański"
        ],
        [
            "AJ",
            [
                "3F"
            ],
            "Chemia"
        ],
        [
            "AJ",
            [
                "4E"
            ],
            "Chemia"
        ],
        null,
        null,
        null,
        null
    ],
    "3": [
        null,
        [
            "MW",
            [
                "2C"
            ],
            "Chemia"
        ],
        [
            "MW",
            [
                "2G"
            ],
            "Chemia"
        ],
        [
            "MW",
            [
                "3A"
            ],
            "Matematyka"
        ],
        [
            "MW",
            [
                "1B"
            ],
            "Chemia"
        ],
        [
            "MW",
            [
                "5C"
            ],
            "Matematyka"
        ],
        [
            "MW",
            [
                "5C"
            ],
            "Matematyka"
        ],
        [
            "MW",
            [
                "2B"
            ],
            "Chemia"
        ],
        null,
        null,
        null
    ],
    "4": [
        null,
        null,
        [
            "MW",
            [
                "1C"
            ],
            "Chemia"
        ],
        [
            "MW",
            [
                "5C"
            ],
            "Matematyka"
        ],
        [
            "AM",
            [
                "2A"
            ],
            "Historia"
        ],
        [
            "LA",
            [
                "4E"
            ],
            "Język polski"
        ],
        [
            "SG",
            [
                "5A"
            ],
            "Język polski"
        ],
        [
            "SG",
            [
                "5A"
            ],
            "Język polski"
        ],
        [
            "OM",
            [
                "4A-3/6",
                "4B-3/6"
            ],
            "Język hiszpański"
        ],
        null,
        null
    ]
}