{
    "0": [
        null,
        [
            "WS",
            [
                "5B"
            ],
            "Historia"
        ],
        [
            "WS",
            [
                "2C"
            ],
            "Historia D_DW"
        ],
        [
            "WS",
            [
                "4D"
            ],
            "Wiedza o społeczeństwie D_DW"
        ],
        [
            "WS",
            [
                "5C"
            ],
            "Historia D_DW"
        ],
        [
            "WS",
            [
                "3B"
            ],
            "Zajęcia z wychowawcą"
        ],
        [
            "WS",
            [
                "3B"
            ],
            "Historia D_DW"
        ],
        [
            "DS",
            [
                "4B"
            ],
            "Matematyka"
        ],
        [
            "DS",
            [
                "4B"
            ],
            "Matematyka"
        ],
        null,
        null
    ],
    "1": [
        null,
        null,
        null,
        [
            "SZ",
            [
                "2B"
            ],
            "Urządzenia techniki komputerowej"
        ],
        [
            "JJ",
            [
                "2H"
            ],
            "Infrastruktura kolejowa"
        ],
        [
            "SU",
            [
                "2B"
            ],
            "Biologia"
        ],
        [
            "SU",
            [
                "2G"
            ],
            "Biologia"
        ],
        [
            "SU",
            [
                "4B"
            ],
            "Biologia"
        ],
        null,
        null,
        null
    ],
    "2": [
        null,
        [
            "MJ",
            [
                "3E"
            ],
            "HiT"
        ],
        [
            "SU",
            [
                "2H"
            ],
            "Biologia"
        ],
        [
            "SU",
            [
                "3B"
            ],
            "Biologia"
        ],
        [
            "SU",
            [
                "2F"
            ],
            "Zajęcia z wychowawcą"
        ],
        [
            "SU",
            [
                "3E"
            ],
            "Biologia"
        ],
        [
            "SU",
            [
                "2F"
            ],
            "Biologia"
        ],
        [
            "SU",
            [
                "4E"
            ],
            "Biologia"
        ],
        null,
        null,
        null
    ],
    "3": [
        null,
        null,
        [
            "AM",
            [
                "2F"
            ],
            "HiT"
        ],
        [
            "AM",
            [
                "2F"
            ],
            "Historia"
        ],
        null,
        [
            "AM",
            [
                "1A"
            ],
            "Zajęcia z wychowawcą"
        ],
        [
            "AM",
            [
                "2B"
            ],
            "HiT"
        ],
        [
            "AM",
            [
                "2G"
            ],
            "Historia"
        ],
        null,
        null,
        null
    ],
    "4": [
        [
            "MJ",
            [
                "3A"
            ],
            "HiT"
        ],
        [
            "MJ",
            [
                "3C"
            ],
            "HiT"
        ],
        [
            "SZ",
            [
                "1A"
            ],
            "Urządzenia techniki komputerowej"
        ],
        [
            "SU",
            [
                "2C"
            ],
            "Biologia"
        ],
        [
            "SU",
            [
                "4C"
            ],
            "Biologia"
        ],
        [
            "SU",
            [
                "2A"
            ],
            "Biologia"
        ],
        [
            "WS",
            [
                "4D"
            ],
            "Historia D_DW"
        ],
        [
            "SU",
            [
                "4D"
            ],
            "Biologia"
        ],
        [
            "AM",
            [
                "2A"
            ],
            "Etyka"
        ],
        [
            "AM",
            [
                "2A"
            ],
            "Etyka"
        ],
        null
    ]
}