{
    "0": [
        null,
        null,
        null,
        null,
        [
            [
                "4F-1/2-1/2"
            ],
            "Pracowniaorganizacjipracystacji",
            "31"
        ],
        [
            [
                "4F-1/2-1/2"
            ],
            "Pracowniaorganizacjipracystacji",
            "31"
        ],
        [
            [
                "4F-1/2-1/2"
            ],
            "Pracowniaorganizacjipracystacji",
            "31"
        ],
        [
            [
                "2H-1/2-1/2"
            ],
            "Pracowniaruchukolejowego",
            "31"
        ],
        [
            [
                "2H-1/2-1/2"
            ],
            "Pracowniaruchukolejowego",
            "31"
        ],
        null,
        null
    ],
    "1": [
        null,
        null,
        null,
        null,
        null,
        null,
        null,
        null,
        null,
        null,
        null
    ],
    "2": [
        null,
        null,
        null,
        null,
        null,
        null,
        null,
        null,
        null,
        null,
        null
    ],
    "3": [
        null,
        null,
        null,
        null,
        null,
        null,
        null,
        null,
        null,
        null,
        null
    ],
    "4": [
        null,
        null,
        null,
        null,
        null,
        null,
        null,
        null,
        [
            [
                "2H-2/2-2/2"
            ],
            "Pracowniaruchukolejowego",
            "B105"
        ],
        [
            [
                "2H-2/2-2/2"
            ],
            "Pracowniaruchukolejowego",
            "B105"
        ],
        null
    ]
}