{
    "0": [
        null,
        null,
        null,
        null,
        null,
        null,
        [
            [
                "4D"
            ],
            "Pracowniaaplikacjiwebowych-2/2",
            "51"
        ],
        [
            [
                "4C"
            ],
            "Pracowniaaplikacjiwebowych-2/2",
            "51"
        ],
        [
            [
                "4C"
            ],
            "Pracowniaaplikacjiwebowych-1/2",
            "51"
        ],
        [
            [
                "4D"
            ],
            "Pracowniaaplikacjiwebowych-2/2",
            "51"
        ],
        [
            [
                "4D"
            ],
            "Pracowniaaplikacjiwebowych-1/2",
            "51"
        ]
    ],
    "1": [
        null,
        null,
        null,
        null,
        null,
        null,
        null,
        null,
        null,
        null,
        null
    ],
    "2": [
        [
            [
                "4C"
            ],
            "Pracowniaprogramowaniaaplikacjimobilnych-2/2",
            "40"
        ],
        [
            [
                "4C"
            ],
            "Pracowniaprogramowaniaaplikacjimobilnych-2/2",
            "40"
        ],
        [
            [
                "4D"
            ],
            "Pracowniaprogramowaniaaplikacjimobilnych-2/2",
            "40"
        ],
        [
            [
                "4D"
            ],
            "Pracowniaprogramowaniaaplikacjimobilnych-2/2",
            "40"
        ],
        null,
        [
            [
                "4D"
            ],
            "Pracowniaaplikacjiwebowych-1/2",
            "40"
        ],
        [
            [
                "4C"
            ],
            "Programowanieaplikacjiwebowych",
            "33"
        ],
        [
            [
                "4D"
            ],
            "Programowanieaplikacjiwebowych",
            "33"
        ],
        null,
        [
            [
                "4C"
            ],
            "Pracowniaaplikacjiwebowych-1/2",
            "40"
        ],
        [
            [
                "4C"
            ],
            "Programowanieaplikacjimobilnych",
            "44"
        ]
    ],
    "3": [
        [
            [
                "4D"
            ],
            "Programowanieaplikacjimobilnych",
            "57"
        ],
        null,
        [
            [
                "4C"
            ],
            "Pracowniaaplikacjiwebowych-2/2",
            "50"
        ],
        null,
        null,
        null,
        null,
        null,
        null,
        null,
        null
    ],
    "4": [
        null,
        null,
        null,
        null,
        null,
        null,
        null,
        null,
        null,
        null,
        null
    ]
}